pdubuild/__init__.py
pdubuild/__main__.py
pdubuild/bitting.py
pdubuild/py.typed
pdubuild/sms_submit.py
pdubuild/tooling.py
pdubuild/util.py
pdubuild-0.0.3.dist-info/LICENCE.txt
pdubuild-0.0.3.dist-info/METADATA
pdubuild-0.0.3.dist-info/WHEEL
pdubuild-0.0.3.dist-info/top_level.txt
pdubuild-0.0.3.dist-info/RECORD
